Metadata-Version: 1.0
Name: isovectpy
Version: 1.3
Summary: A efficient and accurate simulator for isotope pattern in mass spectrometry
Home-page: http://github.com/isovectpy
Author: Felix Wang
Author-email: felixwang08@hotmail.com
License: MIT
Platform: UNKNOWN
